rubble.py
rubble_lang-0.2.1.dist-info/METADATA
rubble_lang-0.2.1.dist-info/WHEEL
rubble_lang-0.2.1.dist-info/entry_points.txt
rubble_lang-0.2.1.dist-info/top_level.txt
rubble_lang-0.2.1.dist-info/RECORD
