Metadata-Version: 2.4
Name: rubble-lang
Version: 0.2.1
Summary: A bad programming language based on Python.
Author: Ayaan Grover
Author-email: ayaan@example.com
Classifier: Programming Language :: Python :: 3
Classifier: License :: OSI Approved :: MIT License
Classifier: Operating System :: OS Independent
Requires-Python: >=3.7
Dynamic: author
Dynamic: author-email
Dynamic: classifier
Dynamic: requires-python
Dynamic: summary
